Workbook

Sheet Instruções
A1: Conferência dos dez casos de teste do cálculo (B08)
A2: OrçaMarcenaria — TCC de Taiane Queirós Rufatto. Fonte dos dados: evidencias/testes/casos-de-teste-referencia.csv.
A4: Como conferir
A5: 1. Abra cada aba CT01 a CT10. As células em azul são os dados do caso (vieram do CSV); todas as demais são fórmulas.
A6: 2. Clique nas fórmulas e confira se seguem as regras abaixo (regras-de-calculo.md §2). Se quiser, refaça alguma conta na calculadora.
A7: 3. Na aba Resumo, a coluna "Situação" mostra "Confere" quando a planilha chega exatamente ao valor de referência.
A8: 4. Preencha as células em amarelo da aba Resumo (quem conferiu e a data). Com isso, o B08 fica resolvido.
A10: Legenda de cores
A11: Azul: dado de entrada do caso (do CSV) · Preto: fórmula · Verde: fórmula que busca outra aba · Amarelo: você preenche
A13: Regras usadas nas fórmulas (regras-de-calculo.md)
A14: Passos 1 e 2 — Valor da linha = ARRED(quantidade × valor unitário; 2) (RN01, RN02)
A15: Passos 3 a 5 — Subtotal de materiais, de serviços e total de adicionais = soma das linhas já arredondadas (RN-C03, RN04)
... A23: A planilha calcula com o ponto flutuante do Excel; o sistema usa decimal exato. Se algum caso mostrar "DIVERGE", anote e avise antes de corrigir qualquer coisa.

Sheet Resumo
A1: Resumo da conferência dos dez casos
A3: Conferido por | B3: Taiane Rufatto | C3: Preencha as células em amarelo ao terminar a conferência.
A4: Data da conferência | B4: 46295
A6: Caso | B6: Descrição | C6: Custo direto (planilha) | D6: Preço bruto (planilha) | E6: Preço final (planilha) | F6: Preço final (referência) | G6: Diferença | H6: Situação
A7: CT01 | B7: Um material, sem serviço e sem adicional, lucro zero | C7: ='CT01'!B21 -> 289.9 | D7: ='CT01'!B22 -> 289.9 | E7: ='CT01'!B25 -> 289.9 | F7: 289.9 | G7: =ROUND(E7-F7,2) -> 0 | H7: =IF(AND('CT01'!D18=0,'CT01'!D19=0,'CT01'!D20=0,'CT01'!D21=0,'CT01'!D22=0,'CT01'!D23=0,'CT01'!D24=0,'CT01'!D25=0),"Confere","DIVERGE") -> Confere
A8: CT02 | B8: Quantidade fracionada de chapa, margem 30% | C8: ='CT02'!B21 -> 724.75 | D8: ='CT02'!B22 -> 1035.36 | E8: ='CT02'!B25 -> 1035.36 | F8: 1035.36 | G8: =ROUND(E8-F8,2) -> 0 | H8: =IF(AND('CT02'!D18=0,'CT02'!D19=0,'CT02'!D20=0,'CT02'!D21=0,'CT02'!D22=0,'CT02'!D23=0,'CT02'!D24=0,'CT02'!D25=0),"Confere","DIVERGE") -> Confere
A9: CT03 | B9: Orçamento completo (exemplo de referência), margem 30%, dezena | C9: ='CT03'!B27 -> 1931.1 | D9: ='CT03'!B28 -> 2758.71 | E9: ='CT03'!B31 -> 2760 | F9: 2760 | G9: =ROUND(E9-F9,2) -> 0 | H9: =IF(AND('CT03'!D24=0,'CT03'!D25=0,'CT03'!D26=0,'CT03'!D27=0,'CT03'!D28=0,'CT03'!D29=0,'CT03'!D30=0,'CT03'!D31=0),"Confere","DIVERGE") -> Confere
A10: CT04 | B10: Mesmo custo do CT03 com markup 30% (comparação de modos) | C10: ='CT04'!B27 -> 1931.1 | D10: ='CT04'!B28 -> 2510.43 | E10: ='CT04'!B31 -> 2520 | F10: 2520 | G10: =ROUND(E10-F10,2) -> 0 | H10: =IF(AND('CT04'!D24=0,'CT04'!D25=0,'CT04'!D26=0,'CT04'!D27=0,'CT04'!D28=0,'CT04'!D29=0,'CT04'!D30=0,'CT04'!D31=0),"Confere","DIVERGE") -> Confere
A11: CT05 | B11: Arredondamento meio para cima na linha (4,5 x 1,2350 = 5,5575) | C11: ='CT05'!B22 -> 41.55 | D11: ='CT05'!B23 -> 51.94 | E11: ='CT05'!B26 -> 51.94 | F11: 51.94 | G11: =ROUND(E11-F11,2) -> 0 | H11: =IF(AND('CT05'!D19=0,'CT05'!D20=0,'CT05'!D21=0,'CT05'!D22=0,'CT05'!D23=0,'CT05'!D24=0,'CT05'!D25=0,'CT05'!D26=0),"Confere","DIVERGE") -> Confere
A12: CT06 | B12: Somente serviços, markup 50%, arredondamento em real inteiro | C12: ='CT06'!B22 -> 622.5 | D12: ='CT06'!B23 -> 933.75 | E12: ='CT06'!B26 -> 934 | F12: 934 | G12: =ROUND(E12-F12,2) -> 0 | H12: =IF(AND('CT06'!D19=0,'CT06'!D20=0,'CT06'!D21=0,'CT06'!D22=0,'CT06'!D23=0,'CT06'!D24=0,'CT06'!D25=0,'CT06'!D26=0),"Confere","DIVERGE") -> Confere
A13: CT07 | B13: Um item e dois custos adicionais, margem 45%, dezena | C13: ='CT07'!B22 -> 746.25 | D13: ='CT07'!B23 -> 1356.82 | E13: ='CT07'!B26 -> 1360 | F13: 1360 | G13: =ROUND(E13-F13,2) -> 0 | H13: =IF(AND('CT07'!D19=0,'CT07'!D20=0,'CT07'!D21=0,'CT07'!D22=0,'CT07'!D23=0,'CT07'!D24=0,'CT07'!D25=0,'CT07'!D26=0),"Confere","DIVERGE") -> Confere
A14: CT08 | B14: Doze itens, margem 25%, duas casas | C14: ='CT08'!B32 -> 3832.57 | D14: ='CT08'!B33 -> 5110.09 | E14: ='CT08'!B36 -> 5110.09 | F14: 5110.09 | G14: =ROUND(E14-F14,2) -> 0 | H14: =IF(AND('CT08'!D29=0,'CT08'!D30=0,'CT08'!D31=0,'CT08'!D32=0,'CT08'!D33=0,'CT08'!D34=0,'CT08'!D35=0,'CT08'!D36=0),"Confere","DIVERGE") -> Confere
A15: CT09 | B15: Margem alta (60%) com arredondamento em real inteiro | C15: ='CT09'!B22 -> 1392.74 | D15: ='CT09'!B23 -> 3481.85 | E15: ='CT09'!B26 -> 3482 | F15: 3482 | G15: =ROUND(E15-F15,2) -> 0 | H15: =IF(AND('CT09'!D19=0,'CT09'!D20=0,'CT09'!D21=0,'CT09'!D22=0,'CT09'!D23=0,'CT09'!D24=0,'CT09'!D25=0,'CT09'!D26=0),"Confere","DIVERGE") -> Confere
A16: CT10 | B16: Valores mínimos: um serviço de 0,5 hora, markup 0% | C16: ='CT10'!B21 -> 22.5 | D16: ='CT10'!B22 -> 22.5 | E16: ='CT10'!B25 -> 22.5 | F16: 22.5 | G16: =ROUND(E16-F16,2) -> 0 | H16: =IF(AND('CT10'!D18=0,'CT10'!D19=0,'CT10'!D20=0,'CT10'!D21=0,'CT10'!D22=0,'CT10'!D23=0,'CT10'!D24=0,'CT10'!D25=0),"Confere","DIVERGE") -> Confere
A17: Total | G17: =SUM(G7:G16) -> 0 | H17: =COUNTIF(H7:H16,"Confere")&" de 10 conferem" -> 10 de 10 conferem

Sheet CT01
A1: CT01 — Um material, sem serviço e sem adicional, lucro zero
A3: Modo de lucro | B3: margem
A4: Percentual de lucro (pontos %) | B4: 0
A5: Regra de arredondamento | B5: duas_casas
A8: Itens (passos 1 e 2)
A9: Tipo | B9: Descrição | C9: Quantidade | D9: Valor unitário | E9: Valor da linha
A10: material | B10: MDF 18mm | C10: 1 | D10: 289.9 | E10: =ROUND(C10*D10,2) -> 289.9
A12: Custos adicionais (passo 5)
A13: Descrição | B13: Valor
A14: (nenhum) | B14: 0
A16: Fechamento (passos 3 a 9)
A17: Etapa | B17: Planilha | C17: Referência (CSV) | D17: Diferença
A18: Subtotal de materiais | B18: =SUMIF($A$10:$A$10,"material",$E$10:$E$10) -> 289.9 | C18: 289.9 | D18: =ROUND(B18-C18,2) -> 0
A19: Subtotal de serviços | B19: =SUMIF($A$10:$A$10,"servico",$E$10:$E$10) -> 0 | C19: 0 | D19: =ROUND(B19-C19,2) -> 0
A20: Total de custos adicionais | B20: =SUM(B14:B14) -> 0 | C20: 0 | D20: =ROUND(B20-C20,2) -> 0
A21: Custo direto total | B21: =B18+B19+B20 -> 289.9 | C21: 289.9 | D21: =ROUND(B21-C21,2) -> 0
A22: Preço bruto | B22: =IF($B$3="margem",ROUND(B21/(1-$B$4/100),2),ROUND(B21*(1+$B$4/100),2)) -> 289.9 | C22: 289.9 | D22: =ROUND(B22-C22,2) -> 0
A23: Valor do lucro | B23: =B22-B21 -> 0 | C23: 0 | D23: =ROUND(B23-C23,2) -> 0
A24: Ajuste de arredondamento | B24: =B25-B22 -> 0 | C24: 0 | D24: =ROUND(B24-C24,2) -> 0
A25: Preço final | B25: =IF($B$5="real_inteiro",ROUNDUP(B22,0),IF($B$5="dezena",ROUNDUP(B22/10,0)*10,B22)) -> 289.9 | C25: 289.9 | D25: =ROUND(B25-C25,2) -> 0

Sheet CT02
A1: CT02 — Quantidade fracionada de chapa, margem 30%
A3: Modo de lucro | B3: margem
A4: Percentual de lucro (pontos %) | B4: 30
A5: Regra de arredondamento | B5: duas_casas
A8: Itens (passos 1 e 2)
A9: Tipo | B9: Descrição | C9: Quantidade | D9: Valor unitário | E9: Valor da linha
A10: material | B10: MDF 18mm | C10: 2.5 | D10: 289.9 | E10: =ROUND(C10*D10,2) -> 724.75
A12: Custos adicionais (passo 5)
A13: Descrição | B13: Valor
A14: (nenhum) | B14: 0
A16: Fechamento (passos 3 a 9)
A17: Etapa | B17: Planilha | C17: Referência (CSV) | D17: Diferença
A18: Subtotal de materiais | B18: =SUMIF($A$10:$A$10,"material",$E$10:$E$10) -> 724.75 | C18: 724.75 | D18: =ROUND(B18-C18,2) -> 0
A19: Subtotal de serviços | B19: =SUMIF($A$10:$A$10,"servico",$E$10:$E$10) -> 0 | C19: 0 | D19: =ROUND(B19-C19,2) -> 0
A20: Total de custos adicionais | B20: =SUM(B14:B14) -> 0 | C20: 0 | D20: =ROUND(B20-C20,2) -> 0
A21: Custo direto total | B21: =B18+B19+B20 -> 724.75 | C21: 724.75 | D21: =ROUND(B21-C21,2) -> 0
A22: Preço bruto | B22: =IF($B$3="margem",ROUND(B21/(1-$B$4/100),2),ROUND(B21*(1+$B$4/100),2)) -> 1035.36 | C22: 1035.36 | D22: =ROUND(B22-C22,2) -> 0
A23: Valor do lucro | B23: =B22-B21 -> 310.61 | C23: 310.61 | D23: =ROUND(B23-C23,2) -> 0
A24: Ajuste de arredondamento | B24: =B25-B22 -> 0 | C24: 0 | D24: =ROUND(B24-C24,2) -> 0
A25: Preço final | B25: =IF($B$5="real_inteiro",ROUNDUP(B22,0),IF($B$5="dezena",ROUNDUP(B22/10,0)*10,B22)) -> 1035.36 | C25: 1035.36 | D25: =ROUND(B25-C25,2) -> 0

Sheet CT03
A1: CT03 — Orçamento completo (exemplo de referência), margem 30%, dezena
A3: Modo de lucro | B3: margem
A4: Percentual de lucro (pontos %) | B4: 30
A5: Regra de arredondamento | B5: dezena
A8: Itens (passos 1 e 2)
A9: Tipo | B9: Descrição | C9: Quantidade | D9: Valor unitário | E9: Valor da linha
A10: material | B10: MDF 18mm | C10: 2.5 | D10: 289.9 | E10: =ROUND(C10*D10,2) -> 724.75
A11: material | B11: Fita de borda | C11: 30 | D11: 1.235 | E11: =ROUND(C11*D11,2) -> 37.05
A12: material | B12: Corrediça | C12: 6 | D12: 34.5 | E12: =ROUND(C12*D12,2) -> 207
A13: material | B13: Dobradiça | C13: 12 | D13: 8.9 | E13: =ROUND(C13*D13,2) -> 106.8
A14: servico | B14: Corte e usinagem | C14: 8 | D14: 45 | E14: =ROUND(C14*D14,2) -> 360
A15: servico | B15: Montagem | C15: 6 | D15: 55 | E15: =ROUND(C15*D15,2) -> 330
A17: Custos adicionais (passo 5)
A18: Descrição | B18: Valor
A19: Frete | B19: 120
A20: Ferragens diversas | B20: 45.5
A22: Fechamento (passos 3 a 9)
A23: Etapa | B23: Planilha | C23: Referência (CSV) | D23: Diferença
A24: Subtotal de materiais | B24: =SUMIF($A$10:$A$15,"material",$E$10:$E$15) -> 1075.6 | C24: 1075.6 | D24: =ROUND(B24-C24,2) -> 0
A25: Subtotal de serviços | B25: =SUMIF($A$10:$A$15,"servico",$E$10:$E$15) -> 690 | C25: 690 | D25: =ROUND(B25-C25,2) -> 0
A26: Total de custos adicionais | B26: =SUM(B19:B20) -> 165.5 | C26: 165.5 | D26: =ROUND(B26-C26,2) -> 0
A27: Custo direto total | B27: =B24+B25+B26 -> 1931.1 | C27: 1931.1 | D27: =ROUND(B27-C27,2) -> 0
A28: Preço bruto | B28: =IF($B$3="margem",ROUND(B27/(1-$B$4/100),2),ROUND(B27*(1+$B$4/100),2)) -> 2758.71 | C28: 2758.71 | D28: =ROUND(B28-C28,2) -> 0
A29: Valor do lucro | B29: =B28-B27 -> 827.61 | C29: 827.61 | D29: =ROUND(B29-C29,2) -> 0
A30: Ajuste de arredondamento | B30: =B31-B28 -> 1.29 | C30: 1.29 | D30: =ROUND(B30-C30,2) -> 0
A31: Preço final | B31: =IF($B$5="real_inteiro",ROUNDUP(B28,0),IF($B$5="dezena",ROUNDUP(B28/10,0)*10,B28)) -> 2760 | C31: 2760 | D31: =ROUND(B31-C31,2) -> 0

Sheet CT04
A1: CT04 — Mesmo custo do CT03 com markup 30% (comparação de modos)
A3: Modo de lucro | B3: markup
A4: Percentual de lucro (pontos %) | B4: 30
A5: Regra de arredondamento | B5: dezena
A8: Itens (passos 1 e 2)
A9: Tipo | B9: Descrição | C9: Quantidade | D9: Valor unitário | E9: Valor da linha
A10: material | B10: MDF 18mm | C10: 2.5 | D10: 289.9 | E10: =ROUND(C10*D10,2) -> 724.75
A11: material | B11: Fita de borda | C11: 30 | D11: 1.235 | E11: =ROUND(C11*D11,2) -> 37.05
A12: material | B12: Corrediça | C12: 6 | D12: 34.5 | E12: =ROUND(C12*D12,2) -> 207
A13: material | B13: Dobradiça | C13: 12 | D13: 8.9 | E13: =ROUND(C13*D13,2) -> 106.8
A14: servico | B14: Corte e usinagem | C14: 8 | D14: 45 | E14: =ROUND(C14*D14,2) -> 360
A15: servico | B15: Montagem | C15: 6 | D15: 55 | E15: =ROUND(C15*D15,2) -> 330
A17: Custos adicionais (passo 5)
A18: Descrição | B18: Valor
A19: Frete | B19: 120
A20: Ferragens diversas | B20: 45.5
A22: Fechamento (passos 3 a 9)
A23: Etapa | B23: Planilha | C23: Referência (CSV) | D23: Diferença
A24: Subtotal de materiais | B24: =SUMIF($A$10:$A$15,"material",$E$10:$E$15) -> 1075.6 | C24: 1075.6 | D24: =ROUND(B24-C24,2) -> 0
A25: Subtotal de serviços | B25: =SUMIF($A$10:$A$15,"servico",$E$10:$E$15) -> 690 | C25: 690 | D25: =ROUND(B25-C25,2) -> 0
A26: Total de custos adicionais | B26: =SUM(B19:B20) -> 165.5 | C26: 165.5 | D26: =ROUND(B26-C26,2) -> 0
A27: Custo direto total | B27: =B24+B25+B26 -> 1931.1 | C27: 1931.1 | D27: =ROUND(B27-C27,2) -> 0
A28: Preço bruto | B28: =IF($B$3="margem",ROUND(B27/(1-$B$4/100),2),ROUND(B27*(1+$B$4/100),2)) -> 2510.43 | C28: 2510.43 | D28: =ROUND(B28-C28,2) -> 0
A29: Valor do lucro | B29: =B28-B27 -> 579.33 | C29: 579.33 | D29: =ROUND(B29-C29,2) -> 0
A30: Ajuste de arredondamento | B30: =B31-B28 -> 9.57 | C30: 9.57 | D30: =ROUND(B30-C30,2) -> 0
A31: Preço final | B31: =IF($B$5="real_inteiro",ROUNDUP(B28,0),IF($B$5="dezena",ROUNDUP(B28/10,0)*10,B28)) -> 2520 | C31: 2520 | D31: =ROUND(B31-C31,2) -> 0

Sheet CT05
A1: CT05 — Arredondamento meio para cima na linha (4,5 x 1,2350 = 5,5575)
A3: Modo de lucro | B3: margem
A4: Percentual de lucro (pontos %) | B4: 20
A5: Regra de arredondamento | B5: duas_casas
A8: Itens (passos 1 e 2)
A9: Tipo | B9: Descrição | C9: Quantidade | D9: Valor unitário | E9: Valor da linha
A10: material | B10: Fita de borda | C10: 4.5 | D10: 1.235 | E10: =ROUND(C10*D10,2) -> 5.56
A11: material | B11: Cola PVA | C11: 1.5 | D11: 23.99 | E11: =ROUND(C11*D11,2) -> 35.99
A13: Custos adicionais (passo 5)
A14: Descrição | B14: Valor
A15: (nenhum) | B15: 0
A17: Fechamento (passos 3 a 9)
A18: Etapa | B18: Planilha | C18: Referência (CSV) | D18: Diferença
A19: Subtotal de materiais | B19: =SUMIF($A$10:$A$11,"material",$E$10:$E$11) -> 41.55 | C19: 41.55 | D19: =ROUND(B19-C19,2) -> 0
A20: Subtotal de serviços | B20: =SUMIF($A$10:$A$11,"servico",$E$10:$E$11) -> 0 | C20: 0 | D20: =ROUND(B20-C20,2) -> 0
A21: Total de custos adicionais | B21: =SUM(B15:B15) -> 0 | C21: 0 | D21: =ROUND(B21-C21,2) -> 0
A22: Custo direto total | B22: =B19+B20+B21 -> 41.55 | C22: 41.55 | D22: =ROUND(B22-C22,2) -> 0
A23: Preço bruto | B23: =IF($B$3="margem",ROUND(B22/(1-$B$4/100),2),ROUND(B22*(1+$B$4/100),2)) -> 51.94 | C23: 51.94 | D23: =ROUND(B23-C23,2) -> 0
A24: Valor do lucro | B24: =B23-B22 -> 10.39 | C24: 10.39 | D24: =ROUND(B24-C24,2) -> 0
A25: Ajuste de arredondamento | B25: =B26-B23 -> 0 | C25: 0 | D25: =ROUND(B25-C25,2) -> 0
A26: Preço final | B26: =IF($B$5="real_inteiro",ROUNDUP(B23,0),IF($B$5="dezena",ROUNDUP(B23/10,0)*10,B23)) -> 51.94 | C26: 51.94 | D26: =ROUND(B26-C26,2) -> 0

Sheet CT06
A1: CT06 — Somente serviços, markup 50%, arredondamento em real inteiro
A3: Modo de lucro | B3: markup
A4: Percentual de lucro (pontos %) | B4: 50
A5: Regra de arredondamento | B5: real_inteiro
A8: Itens (passos 1 e 2)
A9: Tipo | B9: Descrição | C9: Quantidade | D9: Valor unitário | E9: Valor da linha
A10: servico | B10: Projeto 3D | C10: 4 | D10: 80 | E10: =ROUND(C10*D10,2) -> 320
A11: servico | B11: Instalação | C11: 5.5 | D11: 55 | E11: =ROUND(C11*D11,2) -> 302.5
A13: Custos adicionais (passo 5)
A14: Descrição | B14: Valor
A15: (nenhum) | B15: 0
A17: Fechamento (passos 3 a 9)
A18: Etapa | B18: Planilha | C18: Referência (CSV) | D18: Diferença
A19: Subtotal de materiais | B19: =SUMIF($A$10:$A$11,"material",$E$10:$E$11) -> 0 | C19: 0 | D19: =ROUND(B19-C19,2) -> 0
A20: Subtotal de serviços | B20: =SUMIF($A$10:$A$11,"servico",$E$10:$E$11) -> 622.5 | C20: 622.5 | D20: =ROUND(B20-C20,2) -> 0
A21: Total de custos adicionais | B21: =SUM(B15:B15) -> 0 | C21: 0 | D21: =ROUND(B21-C21,2) -> 0
A22: Custo direto total | B22: =B19+B20+B21 -> 622.5 | C22: 622.5 | D22: =ROUND(B22-C22,2) -> 0
A23: Preço bruto | B23: =IF($B$3="margem",ROUND(B22/(1-$B$4/100),2),ROUND(B22*(1+$B$4/100),2)) -> 933.75 | C23: 933.75 | D23: =ROUND(B23-C23,2) -> 0
A24: Valor do lucro | B24: =B23-B22 -> 311.25 | C24: 311.25 | D24: =ROUND(B24-C24,2) -> 0
A25: Ajuste de arredondamento | B25: =B26-B23 -> 0.25 | C25: 0.25 | D25: =ROUND(B25-C25,2) -> 0
A26: Preço final | B26: =IF($B$5="real_inteiro",ROUNDUP(B23,0),IF($B$5="dezena",ROUNDUP(B23/10,0)*10,B23)) -> 934 | C26: 934 | D26: =ROUND(B26-C26,2) -> 0

Sheet CT07
A1: CT07 — Um item e dois custos adicionais, margem 45%, dezena
A3: Modo de lucro | B3: margem
A4: Percentual de lucro (pontos %) | B4: 45
A5: Regra de arredondamento | B5: dezena
A8: Itens (passos 1 e 2)
A9: Tipo | B9: Descrição | C9: Quantidade | D9: Valor unitário | E9: Valor da linha
A10: material | B10: Chapa MDP 15mm | C10: 3 | D10: 198.75 | E10: =ROUND(C10*D10,2) -> 596.25
A12: Custos adicionais (passo 5)
A13: Descrição | B13: Valor
A14: Frete | B14: 90
A15: Deslocamento | B15: 60
A17: Fechamento (passos 3 a 9)
A18: Etapa | B18: Planilha | C18: Referência (CSV) | D18: Diferença
A19: Subtotal de materiais | B19: =SUMIF($A$10:$A$10,"material",$E$10:$E$10) -> 596.25 | C19: 596.25 | D19: =ROUND(B19-C19,2) -> 0
A20: Subtotal de serviços | B20: =SUMIF($A$10:$A$10,"servico",$E$10:$E$10) -> 0 | C20: 0 | D20: =ROUND(B20-C20,2) -> 0
A21: Total de custos adicionais | B21: =SUM(B14:B15) -> 150 | C21: 150 | D21: =ROUND(B21-C21,2) -> 0
A22: Custo direto total | B22: =B19+B20+B21 -> 746.25 | C22: 746.25 | D22: =ROUND(B22-C22,2) -> 0
A23: Preço bruto | B23: =IF($B$3="margem",ROUND(B22/(1-$B$4/100),2),ROUND(B22*(1+$B$4/100),2)) -> 1356.82 | C23: 1356.82 | D23: =ROUND(B23-C23,2) -> 0
A24: Valor do lucro | B24: =B23-B22 -> 610.57 | C24: 610.57 | D24: =ROUND(B24-C24,2) -> 0
A25: Ajuste de arredondamento | B25: =B26-B23 -> 3.18 | C25: 3.18 | D25: =ROUND(B25-C25,2) -> 0
A26: Preço final | B26: =IF($B$5="real_inteiro",ROUNDUP(B23,0),IF($B$5="dezena",ROUNDUP(B23/10,0)*10,B23)) -> 1360 | C26: 1360 | D26: =ROUND(B26-C26,2) -> 0

Sheet CT08
A1: CT08 — Doze itens, margem 25%, duas casas
A3: Modo de lucro | B3: margem
A4: Percentual de lucro (pontos %) | B4: 25
A5: Regra de arredondamento | B5: duas_casas
A8: Itens (passos 1 e 2)
A9: Tipo | B9: Descrição | C9: Quantidade | D9: Valor unitário | E9: Valor da linha
A10: material | B10: MDF 18mm | C10: 4 | D10: 289.9 | E10: =ROUND(C10*D10,2) -> 1159.6
A11: material | B11: MDF 6mm | C11: 2 | D11: 169.9 | E11: =ROUND(C11*D11,2) -> 339.8
A12: material | B12: Fita de borda | C12: 85 | D12: 1.235 | E12: =ROUND(C12*D12,2) -> 104.98
A13: material | B13: Corrediça | C13: 10 | D13: 34.5 | E13: =ROUND(C13*D13,2) -> 345
A14: material | B14: Dobradiça | C14: 24 | D14: 8.9 | E14: =ROUND(C14*D14,2) -> 213.6
A15: material | B15: Puxador | C15: 12 | D15: 12.75 | E15: =ROUND(C15*D15,2) -> 153
A16: material | B16: Parafuso 4x40 (cento) | C16: 2 | D16: 18.9 | E16: =ROUND(C16*D16,2) -> 37.8
A17: material | B17: Cola PVA | C17: 1 | D17: 23.99 | E17: =ROUND(C17*D17,2) -> 23.99
A18: material | B18: Pé regulável | C18: 8 | D18: 4.35 | E18: =ROUND(C18*D18,2) -> 34.8
A19: servico | B19: Corte e usinagem | C19: 14 | D19: 45 | E19: =ROUND(C19*D19,2) -> 630
A20: servico | B20: Montagem | C20: 10 | D20: 55 | E20: =ROUND(C20*D20,2) -> 550
A21: servico | B21: Projeto 3D | C21: 3 | D21: 80 | E21: =ROUND(C21*D21,2) -> 240
A23: Custos adicionais (passo 5)
A24: Descrição | B24: Valor
A25: (nenhum) | B25: 0
A27: Fechamento (passos 3 a 9)
A28: Etapa | B28: Planilha | C28: Referência (CSV) | D28: Diferença
A29: Subtotal de materiais | B29: =SUMIF($A$10:$A$21,"material",$E$10:$E$21) -> 2412.57 | C29: 2412.57 | D29: =ROUND(B29-C29,2) -> 0
A30: Subtotal de serviços | B30: =SUMIF($A$10:$A$21,"servico",$E$10:$E$21) -> 1420 | C30: 1420 | D30: =ROUND(B30-C30,2) -> 0
A31: Total de custos adicionais | B31: =SUM(B25:B25) -> 0 | C31: 0 | D31: =ROUND(B31-C31,2) -> 0
A32: Custo direto total | B32: =B29+B30+B31 -> 3832.57 | C32: 3832.57 | D32: =ROUND(B32-C32,2) -> 0
A33: Preço bruto | B33: =IF($B$3="margem",ROUND(B32/(1-$B$4/100),2),ROUND(B32*(1+$B$4/100),2)) -> 5110.09 | C33: 5110.09 | D33: =ROUND(B33-C33,2) -> 0
A34: Valor do lucro | B34: =B33-B32 -> 1277.52 | C34: 1277.52 | D34: =ROUND(B34-C34,2) -> 0
A35: Ajuste de arredondamento | B35: =B36-B33 -> 0 | C35: 0 | D35: =ROUND(B35-C35,2) -> 0
A36: Preço final | B36: =IF($B$5="real_inteiro",ROUNDUP(B33,0),IF($B$5="dezena",ROUNDUP(B33/10,0)*10,B33)) -> 5110.09 | C36: 5110.09 | D36: =ROUND(B36-C36,2) -> 0

Sheet CT09
A1: CT09 — Margem alta (60%) com arredondamento em real inteiro
A3: Modo de lucro | B3: margem
A4: Percentual de lucro (pontos %) | B4: 60
A5: Regra de arredondamento | B5: real_inteiro
A8: Itens (passos 1 e 2)
A9: Tipo | B9: Descrição | C9: Quantidade | D9: Valor unitário | E9: Valor da linha
A10: material | B10: Lâmina de madeira nobre | C10: 2.25 | D10: 412.33 | E10: =ROUND(C10*D10,2) -> 927.74
A11: servico | B11: Acabamento manual | C11: 6 | D11: 65 | E11: =ROUND(C11*D11,2) -> 390
A13: Custos adicionais (passo 5)
A14: Descrição | B14: Valor
A15: Frete | B15: 75
A17: Fechamento (passos 3 a 9)
A18: Etapa | B18: Planilha | C18: Referência (CSV) | D18: Diferença
A19: Subtotal de materiais | B19: =SUMIF($A$10:$A$11,"material",$E$10:$E$11) -> 927.74 | C19: 927.74 | D19: =ROUND(B19-C19,2) -> 0
A20: Subtotal de serviços | B20: =SUMIF($A$10:$A$11,"servico",$E$10:$E$11) -> 390 | C20: 390 | D20: =ROUND(B20-C20,2) -> 0
A21: Total de custos adicionais | B21: =SUM(B15:B15) -> 75 | C21: 75 | D21: =ROUND(B21-C21,2) -> 0
A22: Custo direto total | B22: =B19+B20+B21 -> 1392.74 | C22: 1392.74 | D22: =ROUND(B22-C22,2) -> 0
A23: Preço bruto | B23: =IF($B$3="margem",ROUND(B22/(1-$B$4/100),2),ROUND(B22*(1+$B$4/100),2)) -> 3481.85 | C23: 3481.85 | D23: =ROUND(B23-C23,2) -> 0
A24: Valor do lucro | B24: =B23-B22 -> 2089.11 | C24: 2089.11 | D24: =ROUND(B24-C24,2) -> 0
A25: Ajuste de arredondamento | B25: =B26-B23 -> 0.15 | C25: 0.15 | D25: =ROUND(B25-C25,2) -> 0
A26: Preço final | B26: =IF($B$5="real_inteiro",ROUNDUP(B23,0),IF($B$5="dezena",ROUNDUP(B23/10,0)*10,B23)) -> 3482 | C26: 3482 | D26: =ROUND(B26-C26,2) -> 0

Sheet CT10
A1: CT10 — Valores mínimos: um serviço de 0,5 hora, markup 0%
A3: Modo de lucro | B3: markup
A4: Percentual de lucro (pontos %) | B4: 0
A5: Regra de arredondamento | B5: duas_casas
A8: Itens (passos 1 e 2)
A9: Tipo | B9: Descrição | C9: Quantidade | D9: Valor unitário | E9: Valor da linha
A10: servico | B10: Ajuste de porta | C10: 0.5 | D10: 45 | E10: =ROUND(C10*D10,2) -> 22.5
A12: Custos adicionais (passo 5)
A13: Descrição | B13: Valor
A14: (nenhum) | B14: 0
A16: Fechamento (passos 3 a 9)
A17: Etapa | B17: Planilha | C17: Referência (CSV) | D17: Diferença
A18: Subtotal de materiais | B18: =SUMIF($A$10:$A$10,"material",$E$10:$E$10) -> 0 | C18: 0 | D18: =ROUND(B18-C18,2) -> 0
A19: Subtotal de serviços | B19: =SUMIF($A$10:$A$10,"servico",$E$10:$E$10) -> 22.5 | C19: 22.5 | D19: =ROUND(B19-C19,2) -> 0
A20: Total de custos adicionais | B20: =SUM(B14:B14) -> 0 | C20: 0 | D20: =ROUND(B20-C20,2) -> 0
A21: Custo direto total | B21: =B18+B19+B20 -> 22.5 | C21: 22.5 | D21: =ROUND(B21-C21,2) -> 0
A22: Preço bruto | B22: =IF($B$3="margem",ROUND(B21/(1-$B$4/100),2),ROUND(B21*(1+$B$4/100),2)) -> 22.5 | C22: 22.5 | D22: =ROUND(B22-C22,2) -> 0
A23: Valor do lucro | B23: =B22-B21 -> 0 | C23: 0 | D23: =ROUND(B23-C23,2) -> 0
A24: Ajuste de arredondamento | B24: =B25-B22 -> 0 | C24: 0 | D24: =ROUND(B24-C24,2) -> 0
A25: Preço final | B25: =IF($B$5="real_inteiro",ROUNDUP(B22,0),IF($B$5="dezena",ROUNDUP(B22/10,0)*10,B22)) -> 22.5 | C25: 22.5 | D25: =ROUND(B25-C25,2) -> 0
